MD23005UNO/MD23005UNO.py
MD23005UNO/__init__.py
md23005uno-0.7.dist-info/METADATA
md23005uno-0.7.dist-info/WHEEL
md23005uno-0.7.dist-info/top_level.txt
md23005uno-0.7.dist-info/RECORD
