Metadata-Version: 2.4
Name: MD23005UNO
Version: 0.7
Summary: Librería que contiene diferentes métodos para resolver sistemas de ecuaciones lineales
Home-page: https://github.com/MD23005/MD23005UNO.git
Author: Ronald Manzano
Author-email: md23005@ues.edu.sv
Requires-Dist: numpy
Requires-Dist: typing
Dynamic: author
Dynamic: author-email
Dynamic: description
Dynamic: description-content-type
Dynamic: home-page
Dynamic: requires-dist
Dynamic: summary
